numpyk/__init__.py
numpyk/files.py
numpyk-0.0.33.dist-info/METADATA
numpyk-0.0.33.dist-info/WHEEL
numpyk-0.0.33.dist-info/top_level.txt
numpyk-0.0.33.dist-info/RECORD
