Metadata-Version: 2.1
Name: numpyk
Version: 0.0.33
Summary: Alternate to numpy
Author: xhi
Author-email: <changexhiwong@info.in>
Keywords: python
Classifier: Programming Language :: Python :: 3
